json_websocket/__init__.py
json_websocket/basic/__init__.py
json_websocket/basic/abstract_json_socket.py
json_websocket/basic/websocket.py
json_websocket/basic/websocket_data.js
json_websocket/basic/websocket_styles.css
json_websocket/cmd/__init__.py
json_websocket/cmd/abstract_cmd_json_socket.py
json_websocket/cmd/websocket.py
json_websocket/cmd/websocket_data.js
json_websocket/server/__init__.py
json_websocket/server/async_server.py
json_websocket/tests/__init__.py
json_websocket/tests/test_basic.py
json_websocket-0.3.1607693506.dist-info/METADATA
json_websocket-0.3.1607693506.dist-info/WHEEL
json_websocket-0.3.1607693506.dist-info/top_level.txt
json_websocket-0.3.1607693506.dist-info/RECORD
