Metadata-Version: 2.1
Name: json-websocket
Version: 0.3.1607693506
Summary: json-websocket
Home-page: https://github.com/JulianKimmig/json_websocket
Author: Julian Kimmig
Author-email: julian-kimmig@gmx.net
License: UNKNOWN
Platform: UNKNOWN
Classifier: Programming Language :: Python :: 3
Classifier: License :: OSI Approved :: MIT License
Classifier: Operating System :: OS Independent
Requires-Dist: websockets
Requires-Dist: websocket-client
